tests/__init__.py
tests/test_clients.py
xchainpy_thorchain/__init__.py
xchainpy_thorchain/client.py
xchainpy_thorchain/crypto.py
xchainpy_thorchain/utils.py
xchainpy_thorchain/cosmos/__init__.py
xchainpy_thorchain/cosmos/cosmosUtil.py
xchainpy_thorchain/cosmos/message.py
xchainpy_thorchain/cosmos/sdk_client.py
xchainpy_thorchain/cosmos/models/AminoWrapping.py
xchainpy_thorchain/cosmos/models/Coin.py
xchainpy_thorchain/cosmos/models/Msg.py
xchainpy_thorchain/cosmos/models/MsgCoin.py
xchainpy_thorchain/cosmos/models/MsgNativeTx.py
xchainpy_thorchain/cosmos/models/StdSignature.py
xchainpy_thorchain/cosmos/models/StdTx.py
xchainpy_thorchain/cosmos/models/StdTxFee.py
xchainpy_thorchain/cosmos/models/Tx.py
xchainpy_thorchain/cosmos/models/__init__.py
xchainpy_thorchain-0.2.0.dist-info/LICENSE
xchainpy_thorchain-0.2.0.dist-info/METADATA
xchainpy_thorchain-0.2.0.dist-info/WHEEL
xchainpy_thorchain-0.2.0.dist-info/top_level.txt
xchainpy_thorchain-0.2.0.dist-info/RECORD
