Metadata-Version: 2.1
Name: xchainpy-thorchain
Version: 0.2.0
Summary: Thorchain wrapper
Home-page: https://github.com/xchainjs/xchainpy-lib
Author: THORChain
Author-email: 
License: MIT
Keywords: THORChain,XChainpy,xchainpy_thorchain
Platform: UNKNOWN
Classifier: Intended Audience :: Developers
Classifier: Topic :: Software Development :: Libraries :: Python Modules
Classifier: License :: OSI Approved :: MIT License
Classifier: Programming Language :: Python :: 3
Classifier: Programming Language :: Python :: 3.6
Classifier: Programming Language :: Python :: 3.7
Classifier: Programming Language :: Python
License-File: LICENSE
Requires-Dist: xchainpy-crypto (>=0.1.5)
Requires-Dist: py-binance-chain (==0.1)
Requires-Dist: xchainpy-util (>=0.1.5)
Requires-Dist: xchainpy-client (>=0.1.3)
Requires-Dist: mnemonic (==0.19)
Requires-Dist: requests (==2.22.0)
Requires-Dist: http3 (==0.6.7)
Requires-Dist: bech32 (==1.2.0)
Requires-Dist: ecdsa (==0.16.1)
Requires-Dist: hdwallets (==0.1.2)
